huaweicloudsdkcss/__init__.py
huaweicloudsdkcss/v1/__init__.py
huaweicloudsdkcss/v1/css_async_client.py
huaweicloudsdkcss/v1/css_client.py
huaweicloudsdkcss/v1/model/__init__.py
huaweicloudsdkcss/v1/model/actions.py
huaweicloudsdkcss/v1/model/add_favorite_req.py
huaweicloudsdkcss/v1/model/add_favorite_req_template.py
huaweicloudsdkcss/v1/model/add_favorite_request.py
huaweicloudsdkcss/v1/model/add_favorite_response.py
huaweicloudsdkcss/v1/model/add_independent_node_request.py
huaweicloudsdkcss/v1/model/add_independent_node_response.py
huaweicloudsdkcss/v1/model/address_and_ports.py
huaweicloudsdkcss/v1/model/ai_ops.py
huaweicloudsdkcss/v1/model/ai_ops_detector.py
huaweicloudsdkcss/v1/model/ai_ops_risk_object.py
huaweicloudsdkcss/v1/model/ai_ops_setting.py
huaweicloudsdkcss/v1/model/backup_rsp.py
huaweicloudsdkcss/v1/model/batch_add_or_delete_tag_on_cluster_req.py
huaweicloudsdkcss/v1/model/bind_public_req.py
huaweicloudsdkcss/v1/model/bind_public_req_eip.py
huaweicloudsdkcss/v1/model/bind_public_req_eip_band_width.py
huaweicloudsdkcss/v1/model/bind_public_req_eip_req.py
huaweicloudsdkcss/v1/model/certificates_resource.py
huaweicloudsdkcss/v1/model/certs_records_datastore.py
huaweicloudsdkcss/v1/model/change_cluster_subnet_request.py
huaweicloudsdkcss/v1/model/change_cluster_subnet_response.py
huaweicloudsdkcss/v1/model/change_mode_req.py
huaweicloudsdkcss/v1/model/change_mode_request.py
huaweicloudsdkcss/v1/model/change_mode_response.py
huaweicloudsdkcss/v1/model/change_security_group_req.py
huaweicloudsdkcss/v1/model/change_security_group_request.py
huaweicloudsdkcss/v1/model/change_security_group_response.py
huaweicloudsdkcss/v1/model/close_ai_ops_setting_request.py
huaweicloudsdkcss/v1/model/close_ai_ops_setting_response.py
huaweicloudsdkcss/v1/model/close_kibana_public_req.py
huaweicloudsdkcss/v1/model/cluster_change_main_subnet.py
huaweicloudsdkcss/v1/model/cluster_detail_datastore.py
huaweicloudsdkcss/v1/model/cluster_detail_failed_reasons.py
huaweicloudsdkcss-3.1.184.dist-info/METADATA
huaweicloudsdkcss-3.1.184.dist-info/WHEEL
huaweicloudsdkcss-3.1.184.dist-info/licenses/LICENSE
huaweicloudsdkcss-3.1.184.dist-info/RECORD
